alu4bit.v
module alu4bit(
    input [3:0] A,
    input [3:0] B,
    input [2:0] sel,
    output reg [3:0] Y,
    output reg Carry,
    output reg Zero
);
localparam ADD = 3'b000,
           SUB = 3'b001,
           AND_OP = 3'b010,
           OR_OP  = 3'b011,
           XOR_OP = 3'b100,
           NOT_OP = 3'b101,
           SHL    = 3'b110,
           SHR    = 3'b111;
always @(*) begin
    Carry = 0;
    Y = 0;
    case(sel)
        ADD: begin
            {Carry,Y} = A + B;
        end
        SUB: begin
            {Carry,Y} = A - B;
        end
        AND_OP: begin
            Y = A & B;
        end
        OR_OP: begin
            Y = A | B;
        end
        XOR_OP: begin
            Y = A ^ B;
        end
        NOT_OP: begin
            Y = ~A;
        end
        SHL: begin
            Carry = A[3];
            Y = A << 1;
        end
        SHR: begin
            Carry = A[0];
            Y = A >> 1;
        end
        default: begin
            Carry = 0;
            Y = 0;
        end
    endcase
    Zero = (Y == 4'b0000);
end
endmodule

OpenLane/src/mod8counter.v
module mod8_counter(
    input clk,
    input rst,
    output reg [2:0] sel
);

always @(posedge clk or posedge rst)
begin
    if(rst)
        sel <= 3'b000;
    else
        sel <= sel + 1'b1;
end

endmodule

SIMULATION_SOURCEFILE/alutb.v
`timescale 1ns/1ps

module alu_tb;

reg clk;
reg rst;

reg [3:0] A;
reg [3:0] B;

wire [2:0] sel;
wire [3:0] Y;
wire Carry;
wire Zero;

// Counter
mod8_counter counter(
    .clk(clk),
    .rst(rst),
    .sel(sel)
);

// ALU
alu4bit DUT(
    .A(A),
    .B(B),
    .sel(sel),
    .Y(Y),
    .Carry(Carry),
    .Zero(Zero)
);

// Clock Generation
always #5 clk = ~clk;

initial begin

    $dumpfile("alu.vcd");
    $dumpvars(0,alu_tb);

    clk = 0;
    rst = 1;

    A = 4'b1010;
    B = 4'b0011;

    #10 rst = 0;

    // Run through all 8 operations
    #80;

    A = 4'b1110;
    B = 4'b1011;

    // Run through all 8 operations again
    #80;

    $finish;

end

initial begin
    $monitor("Time=%0t  SEL=%b  A=%b  B=%b  Y=%b  Carry=%b  Zero=%b",
              $time,sel,A,B,Y,Carry,Zero);
end

endmodule

SIMULATION_SOURCEFILE/alu.vcd
$date
	Tue Jul 28 12:32:42 2026
$end
$version
	Icarus Verilog
$end
$timescale
	1ps
$end
$scope module alu_tb $end
$var wire 3 ! sel [2:0] $end
$var wire 1 " Zero $end
$var wire 4 # Y [3:0] $end
$var wire 1 $ Carry $end
$var reg 4 % A [3:0] $end
$var reg 4 & B [3:0] $end
$var reg 1 ' clk $end
$var reg 1 ( rst $end
$scope module DUT $end
$var wire 4 ) A [3:0] $end
$var wire 4 * B [3:0] $end
$var wire 3 + sel [2:0] $end
$var parameter 3 , ADD $end
$var parameter 3 - AND_OP $end
$var parameter 3 . NOT_OP $end
$var parameter 3 / OR_OP $end
$var parameter 3 0 SHL $end
$var parameter 3 1 SHR $end
$var parameter 3 2 SUB $end
$var parameter 3 3 XOR_OP $end
$var reg 1 $ Carry $end
$var reg 4 4 Y [3:0] $end
$var reg 1 " Zero $end
$upscope $end
$scope module counter $end
$var wire 1 ' clk $end
$var wire 1 ( rst $end
$var reg 3 5 sel [2:0] $end
$upscope $end
$upscope $end
$enddefinitions $end
$comment Show the parameter values. $end
$dumpall
b100 3
b1 2
b111 1
b110 0
b11 /
b101 .
b10 -
b0 ,
$end
#0
$dumpvars
b0 5
b1101 4
b0 +
b11 *
b1010 )
1(
0'
b11 &
b1010 %
0$
b1101 #
0"
b0 !
$end
#5000
1'
#10000
0'
0(
#15000
b111 #
b111 4
b1 !
b1 +
b1 5
1'
#20000
0'
#25000
b10 #
b10 4
b10 !
b10 +
b10 5
1'
#30000
0'
#35000
b1011 #
b1011 4
b11 !
b11 +
b11 5
1'
#40000
0'
#45000
b1001 #
b1001 4
b100 !
b100 +
b100 5
1'
#50000
0'
#55000
b101 #
b101 4
b101 !
b101 +
b101 5
1'
#60000
0'
#65000
1$
b100 #
b100 4
b110 !
b110 +
b110 5
1'
#70000
0'
#75000
b101 #
b101 4
0$
b111 !
b111 +
b111 5
1'
#80000
0'
#85000
b1101 #
b1101 4
b0 !
b0 +
b0 5
1'
#90000
1$
b1001 #
b1001 4
0'
b1011 &
b1011 *
b1110 %
b1110 )
#95000
b11 #
b11 4
0$
b1 !
b1 +
b1 5
1'
#100000
0'
#105000
b1010 #
b1010 4
b10 !
b10 +
b10 5
1'
#110000
0'
#115000
b1111 #
b1111 4
b11 !
b11 +
b11 5
1'
#120000
0'
#125000
b101 #
b101 4
b100 !
b100 +
b100 5
1'
#130000
0'
#135000
b1 #
b1 4
b101 !
b101 +
b101 5
1'
#140000
0'
#145000
1$
b1100 #
b1100 4
b110 !
b110 +
b110 5
1'
#150000
0'
#155000
b111 #
b111 4
0$
b111 !
b111 +
b111 5
1'
#160000
0'
#165000
1$
b1001 #
b1001 4
b0 !
b0 +
b0 5
1'
